xfinance/__init__.py
xfinance/client.py
xfinance/exceptions.py
xfinance_sdk-1.0.3.dist-info/METADATA
xfinance_sdk-1.0.3.dist-info/WHEEL
xfinance_sdk-1.0.3.dist-info/top_level.txt
xfinance_sdk-1.0.3.dist-info/RECORD
